{"filename": "./builds/lambda_layer_poetry/6949dceda7032dbe45d7d27c1b83e96e7f81ec661582e6b75bc11f14ed079069.zip", "runtime": "python3.10", "artifacts_dir": "./builds/lambda_layer_poetry/", "build_plan": [["poetry", "python3.10", "./../server", null], ["zip", "./../server", null]], "docker": {"docker_additional_options": [], "docker_build_root": "", "docker_entrypoint": null, "docker_file": "./../server/Dockerfile", "docker_image": "build-python3.10-poetry", "docker_pip_cache": null, "with_ssh_agent": false}}